setup.py
sokt/__init__.py
sokt/sokt.py
sokt.egg-info/PKG-INFO
sokt.egg-info/SOURCES.txt
sokt.egg-info/dependency_links.txt
sokt.egg-info/not-zip-safe
sokt.egg-info/top_level.txt