Metadata-Version: 1.0
Name: sokt
Version: 0.1.3
Summary: For invoking Socket flows
Home-page: http://viasocket.com	
Author: Viasocket
Author-email: kadamb@walkover.in
License: MIT
Platform: UNKNOWN
